.gitignore
.readthedocs.yaml
Dockerfile
Dockerfile-git
LICENSE.txt
MANIFEST
MANIFEST.in
README.md
main.spec
meta.yaml
musclex.sh
musclex_linux.spec
musclex_mac.spec
musclex_win32.spec
requirements
setup.cfg
setup.py
test_upload_pypi
upload_pypi
AppImageBuilder/AppImageBuilder.yml
AppImageBuilder/requirements.txt
Data/Bio_muscle/107.tif
Data/Bio_muscle/2013.tif
Data/Bio_muscle/2014.tif
Data/Circular_Projection/Mn23-1_30umThick_50umStep_1s_scan_pics/Mn23-1_30umThick_20umStep_1s_diffScan_0170.tif
Data/Circular_Projection/Mn23-1_30umThick_50umStep_1s_scan_pics/Mn23-1_30umThick_20umStep_1s_diffScan_0264.tif
Data/Circular_Projection/Mn23-1_30umThick_50umStep_1s_scan_pics/Mn23-1_30umThick_20umStep_1s_diffScan_0265.tif
Data/Circular_Projection/Mn23-1_30umThick_50umStep_1s_scan_pics/Mn23-1_30umThick_50umStep_1s_diffScan_0002.hdf
Data/Circular_Projection/Mn23-1_30umThick_50umStep_1s_scan_pics/cp_results/rings.csv
Data/Circular_Projection/Mn23-1_30umThick_50umStep_1s_scan_pics/cp_results/summary.csv
Data/Circular_Projection/MnC22-5_30umThick_50umStep_1s/MnC22-5_30umThick_50umStep_1sExp_diffScan_0608.tif
Data/Circular_Projection/MnC22-5_30umThick_50umStep_1s/MnC22-5_30umThick_50umStep_1sExp_diffScan_0609.tif
Data/Circular_Projection/MnC22-5_30umThick_50umStep_1s/MnC22-5_30umThick_50umStep_1sExp_diffScan_0679.tif
Data/Circular_Projection/MnC22-5_30umThick_50umStep_1s/MnC22-5_30umThick_50umStep_1sExp_diffScan_0820.tif
Data/Circular_Projection/MnC22-5_30umThick_50umStep_1s/MnC22-5_30umThick_50umStep_1s_diffScan_0001.hdf
Data/Circular_Projection/MnC22-5_30umThick_50umStep_1s/cp_results/rings.csv
Data/Circular_Projection/MnC22-5_30umThick_50umStep_1s/cp_results/summary.csv
Data/DDF_Processor/Untitled.csv
Data/DDF_Processor/Untitled.xlsx
Data/Diffraction_Centroids/Prep24-1-1-Con.tif
Data/Diffraction_Centroids/Prep24-1-1Rex.tif
Data/LayerLineTraces/p60_1_cont.tif.result.tif
Data/LayerLineTraces/p60_1_rest.tif.result.tif
Data/Quadrant_Folding/p60_1_cont.tif
dev_docs/DevGuide/release-info/libraries
dev_docs/DevGuide/release-info/pipversions_1-14.12_mac.txt
dev_docs/DevGuide/release-info/pipversions_1-15.4.txt
dev_docs/DevGuide/release-info/pipversions_1-15.7.txt
dev_docs/DevGuide/release-info/pipversions_1-20.txt
dev_docs/DevGuide/release-info/pipversions_1-21.1.txt
dev_docs/DevGuide/release-info/pipversions_1-22.0.txt
dev_docs/DevGuide/release-info/pipversions_1-23.0.txt
musclex.egg-info/PKG-INFO
musclex.egg-info/SOURCES.txt
musclex.egg-info/dependency_links.txt
musclex.egg-info/entry_points.txt
musclex.egg-info/pbr.json
musclex.egg-info/requires.txt
musclex.egg-info/top_level.txt
