Metadata-Version: 2.1
Name: musclex
Version: 1.24.0
Summary: Muscle X
Home-page: https://github.com/biocatiit/musclex
Author: BioCAT
Author-email: biocat@lethocerus.biol.iit.edu
Keywords: musclex,biomuscle,diffraction,biocat
Classifier: Development Status :: 3 - Alpha
Classifier: Environment :: X11 Applications :: Qt
Classifier: Intended Audience :: Science/Research
Classifier: Natural Language :: English
Classifier: Operating System :: Other OS
Classifier: Programming Language :: Python
Classifier: Programming Language :: Cython
Classifier: Topic :: Scientific/Engineering :: Bio-Informatics
License-File: LICENSE.txt
